planetequil/__init__.py
planetequil/config.py
planetequil/constants.py
planetequil/data.py
planetequil/loss.py
planetequil/model.py
planetequil/pipeline.py
planetequil/plot.py
planetequil/scripts/main_data.py
planetequil/scripts/main_train.py
planetequil/tests/data/config.yml
planetequil/tests/data/raw/RR_grid.npy
planetequil/tests/data/raw/ZZ_grid.npy
planetequil/tests/data/raw/coils_current.npy
planetequil/tests/data/raw/flux.npy
planetequil/tests/data/raw/mag_measures.npy
planetequil/tests/data/raw/p_profile.npy
planetequil/tests/data/raw/rhs.npy
planetequil/tests/test_config.py
planetequil/tests/test_dataloader.py
planetequil/tests/test_full_pipeline.py
planetequil/tests/test_gs_operator.py
planetequil/tests/test_model.py
planetequil/train.py
planetequil/types.py
planetequil/utils.py
planet_equil-0.1.0.dist-info/LICENSE
planet_equil-0.1.0.dist-info/METADATA
planet_equil-0.1.0.dist-info/WHEEL
planet_equil-0.1.0.dist-info/RECORD
