Metadata-Version: 2.3
Name: planet-equil
Version: 0.1.0
Summary: PlaNet: reconstruction of plasma equilibrium and separatrix using convolutional physics-informed neural operator. See https://doi.org/10.1016/j.fusengdes.2024.114193
License: MIT
Author: Matteo Bonotto
Author-email: m.bonotto@outlook.com
Requires-Python: >=3.10,<3.11
Classifier: License :: OSI Approved :: MIT License
Classifier: Programming Language :: Python :: 3
Classifier: Programming Language :: Python :: 3.10
Requires-Dist: black (>=25.1.0,<26.0.0)
Requires-Dist: datasets (>=3.3.2,<4.0.0)
Requires-Dist: h5py (>=3.13.0,<4.0.0)
Requires-Dist: ipykernel (>=6.29.5,<7.0.0)
Requires-Dist: lightning (>=2.5.1.post0,<3.0.0)
Requires-Dist: matplotlib (>=3.10.1,<4.0.0)
Requires-Dist: mypy (>=1.15.0,<2.0.0)
Requires-Dist: numpy (>=2.0.2,<3.0.0)
Requires-Dist: pandas (>=2.2.3,<3.0.0)
Requires-Dist: plotly (>=6.0.0,<7.0.0)
Requires-Dist: poetry (>=2.1.1,<3.0.0)
Requires-Dist: pytest (>=8.3.5,<9.0.0)
Requires-Dist: scikit-learn (>=1.6.1,<2.0.0)
Requires-Dist: scipy (>=1.15.2,<2.0.0)
Requires-Dist: torch (>=2.7.0,<3.0.0)
Requires-Dist: torchinfo (>=1.8.0,<2.0.0)
Requires-Dist: tqdm (>=4.67.1,<5.0.0)
Requires-Dist: wandb (>=0.19.10,<0.20.0)
